README.rst
setup.cfg
setup.py
xmltag/__init__.py
xmltag/documents.py
xmltag/layout.py
xmltag/nodes.py
xmltag/renderer.py
xmltag/utils.py
xmltag.egg-info/PKG-INFO
xmltag.egg-info/SOURCES.txt
xmltag.egg-info/dependency_links.txt
xmltag.egg-info/top_level.txt