Metadata-Version: 1.1
Name: xmltag
Version: 1.3.1
Summary: Tool for generating HTML and XML documents
Home-page: https://github.com/zenwalker/python-tag
Author: Maxim Poletaev
Author-email: max.poletaev@gmail.com
License: BSD
Keywords: html xml
Platform: UNKNOWN
Classifier: Development Status :: 4 - Beta
Classifier: Programming Language :: Python :: 3.4
Classifier: Programming Language :: Python :: 3.5
